vcnet/__init__.py
vcnet/classifiers.py
vcnet/data.py
vcnet/models.py
vcnet/monotonic_annealing.py
vcnet-0.2.0.dist-info/licenses/LICENSE.txt
vcnet-0.2.0.dist-info/METADATA
vcnet-0.2.0.dist-info/WHEEL
vcnet-0.2.0.dist-info/top_level.txt
vcnet-0.2.0.dist-info/RECORD
