Metadata-Version: 2.4
Name: VCNet
Version: 0.2.0
Summary: Counterfactual generation
Author-email: Thomas Guyet <thomas.guyet@inria.fr>, Victor Guyomard <victor.guyomard@inria.fr>
Maintainer-email: Thomas Guyet <thomas.guyet@inria.fr>
License-Expression: LGPL-3.0-only
Project-URL: Homepage, https://gitlab.inria.fr/tguyet/vcnet/
Project-URL: Repository, https://gitlab.inria.fr/tguyet/vcnet.git
Project-URL: Issues, https://gitlab.inria.fr/tguyet/vcnet/-/issues
Project-URL: Documentation, https://tguyet.gitlabpages.inria.fr/vcnet
Classifier: Programming Language :: Python :: 3
Classifier: Operating System :: OS Independent
Classifier: Topic :: Scientific/Engineering :: Artificial Intelligence
Requires-Python: >=3.7
License-File: LICENSE.txt
Requires-Dist: numpy
Requires-Dist: torch
Requires-Dist: matplotlib
Requires-Dist: pandas
Requires-Dist: scikit-learn
Requires-Dist: scipy
Requires-Dist: lightning
Requires-Dist: xgboost
Provides-Extra: dev
Requires-Dist: pytest; extra == "dev"
Requires-Dist: pytest-cov; extra == "dev"
Dynamic: license-file
